openapi_client/__init__.py
openapi_client/api_client.py
openapi_client/configuration.py
openapi_client/exceptions.py
openapi_client/model_utils.py
openapi_client/rest.py
openapi_client/api/__init__.py
openapi_client/api/administration_audit_log_api.py
openapi_client/api/administration_user_and_group_api.py
openapi_client/api/certificate_management_device_api.py
openapi_client/api/certificate_management_v_manage_api.py
openapi_client/api/cluster_management_api.py
openapi_client/api/colocation_cluster_api.py
openapi_client/api/colocation_service_chain_api.py
openapi_client/api/colocation_service_group_api.py
openapi_client/api/configuration_advanced_inspection_profile_definition_api.py
openapi_client/api/configuration_azure_connect_api.py
openapi_client/api/configuration_circuits_api.py
openapi_client/api/configuration_cloud_express_api.py
openapi_client/api/configuration_cloud_on_ramp_api.py
openapi_client/api/configuration_configuration_group_api.py
openapi_client/api/configuration_dashboard_status_api.py
openapi_client/api/configuration_device_actions_api.py
openapi_client/api/configuration_device_config_history_api.py
openapi_client/api/configuration_device_firmware_update_api.py
openapi_client/api/configuration_device_inventory_api.py
openapi_client/api/configuration_device_software_package_api.py
openapi_client/api/configuration_device_software_update_api.py
openapi_client/api/configuration_device_ssl_proxy_certificate_management_api.py
openapi_client/api/configuration_device_template_api.py
openapi_client/api/configuration_disaster_recovery_api.py
openapi_client/api/configuration_feature_certificate_api.py
openapi_client/api/configuration_feature_profile_mobility_api.py
openapi_client/api/configuration_feature_profile_sdwan_api.py
openapi_client/api/configuration_fqdn_list_builder_api.py
openapi_client/api/configuration_general_template_api.py
openapi_client/api/configuration_multi_cloud_api.py
openapi_client/api/configuration_multidomain_policy_api.py
pied_piper_sdwan_sdk-1.0.51.dist-info/METADATA
pied_piper_sdwan_sdk-1.0.51.dist-info/WHEEL
pied_piper_sdwan_sdk-1.0.51.dist-info/top_level.txt
pied_piper_sdwan_sdk-1.0.51.dist-info/RECORD
