Metadata-Version: 2.1
Name: pied-piper-sdwan-sdk
Version: 1.0.51
Summary: Cisco SD-WAN vManage API
Home-page: 
Author: OpenAPI Generator community
Author-email: vmanage@cisco.com
License: Commercial License
Keywords: OpenAPI,OpenAPI-Generator,Cisco SD-WAN vManage API
Requires-Python: >=3.6
Requires-Dist: urllib3 (>=1.25.3)
Requires-Dist: python-dateutil
